odoo/addons/fieldservice_website_sale/README.rst
odoo/addons/fieldservice_website_sale/__init__.py
odoo/addons/fieldservice_website_sale/__manifest__.py
odoo/addons/fieldservice_website_sale/controllers/__init__.py
odoo/addons/fieldservice_website_sale/controllers/main.py
odoo/addons/fieldservice_website_sale/i18n/ca.po
odoo/addons/fieldservice_website_sale/i18n/es.po
odoo/addons/fieldservice_website_sale/i18n/fieldservice_website_sale.pot
odoo/addons/fieldservice_website_sale/models/__init__.py
odoo/addons/fieldservice_website_sale/models/res_config_settings.py
odoo/addons/fieldservice_website_sale/models/sale_order.py
odoo/addons/fieldservice_website_sale/readme/CONTRIBUTORS.rst
odoo/addons/fieldservice_website_sale/readme/DESCRIPTION.rst
odoo/addons/fieldservice_website_sale/readme/USAGE.rst
odoo/addons/fieldservice_website_sale/static/description/icon.png
odoo/addons/fieldservice_website_sale/static/description/index.html
odoo/addons/fieldservice_website_sale/static/src/js/fsm_calendar.js
odoo/addons/fieldservice_website_sale/static/src/js/payment_form.js
odoo/addons/fieldservice_website_sale/static/src/scss/fsm_calendar.scss
odoo/addons/fieldservice_website_sale/tests/__init__.py
odoo/addons/fieldservice_website_sale/tests/test_fieldservice_website_sale.py
odoo/addons/fieldservice_website_sale/tests/test_res_config_settings.py
odoo/addons/fieldservice_website_sale/tests/test_sale_order.py
odoo/addons/fieldservice_website_sale/views/calendar_templates.xml
odoo/addons/fieldservice_website_sale/views/res_config_settings_views.xml
odoo_addon_fieldservice_website_sale-15.0.1.0.1.1.dist-info/METADATA
odoo_addon_fieldservice_website_sale-15.0.1.0.1.1.dist-info/WHEEL
odoo_addon_fieldservice_website_sale-15.0.1.0.1.1.dist-info/top_level.txt
odoo_addon_fieldservice_website_sale-15.0.1.0.1.1.dist-info/RECORD
